pybarry/__init__.py
pybarry-0.0.7.dist-info/METADATA
pybarry-0.0.7.dist-info/WHEEL
pybarry-0.0.7.dist-info/top_level.txt
pybarry-0.0.7.dist-info/RECORD
