Metadata-Version: 2.1
Name: pybarry
Version: 0.0.7
Summary: Barry Electricity Price Consumption Data
Home-page: https://bitbucket.org/getbarry/pybarry
Author: Barry
Author-email: yash.khatri@barry.energy
License: MIT
Platform: any
Requires-Dist: requests
